wexample_event-0.0.79.dist-info/METADATA
wexample_event-0.0.79.dist-info/WHEEL
wexample_event-0.0.79.dist-info/entry_points.txt
wexample_event/__init__.py
wexample_event/common/__init__.py
wexample_event/common/dispatcher.py
wexample_event/common/listener.py
wexample_event/common/listener_state.py
wexample_event/common/priority.py
wexample_event/dataclass/__init__.py
wexample_event/dataclass/event.py
wexample_event/dataclass/listener_record.py
wexample_event/dataclass/listener_spec.py
wexample_event/py.typed
wexample_event-0.0.79.dist-info/RECORD
